[
    {
        "id": "69a2bc3c853b3",
        "timestamp": "2026-02-28 09:58:20",
        "formType": "contactModal",
        "name": "1",
        "email": "1@gmail.com",
        "phone": "4444",
        "eventType": "",
        "budgetMin": "",
        "budgetMax": "",
        "message": "44",
        "status": "new"
    },
    {
        "id": "69a2bc6b09478",
        "timestamp": "2026-02-28 09:59:07",
        "formType": "test",
        "name": "Test",
        "email": "",
        "phone": "",
        "eventType": "",
        "budgetMin": "",
        "budgetMax": "",
        "message": "",
        "status": "new"
    },
    {
        "id": "69a2bc883c1d9",
        "timestamp": "2026-02-28 09:59:36",
        "formType": "test",
        "name": "Test",
        "email": "",
        "phone": "",
        "eventType": "",
        "budgetMin": "",
        "budgetMax": "",
        "message": "",
        "status": "new"
    },
    {
        "id": "69a2bcb9505cf",
        "timestamp": "2026-02-28 10:00:25",
        "formType": "contactModal",
        "name": "r",
        "email": "r@gmail.com",
        "phone": "4334",
        "eventType": "",
        "budgetMin": "",
        "budgetMax": "",
        "message": "34",
        "status": "new"
    },
    {
        "id": "69a2bccc2ccba",
        "timestamp": "2026-02-28 10:00:44",
        "formType": "contactForm",
        "name": "fdf",
        "email": "dfdf@gmail.com",
        "phone": "",
        "eventType": "wedding",
        "budgetMin": 110000,
        "budgetMax": 200000,
        "message": "df",
        "status": "new"
    },
    {
        "id": "69a2c16d6932c",
        "timestamp": "2026-02-28 10:20:29",
        "formType": "contactForm",
        "name": "dff",
        "email": "dfsdf@gmail.com",
        "phone": "",
        "eventType": "corporate",
        "budgetMin": 50000,
        "budgetMax": 200000,
        "message": "rt",
        "status": "new"
    }
]